elasticsearch_utils/__init__.py
elasticsearch_utils/es.py
elasticsearch_utils/explain_utils.py
elasticsearch_utils/response.py
elasticsearch_utils/results.py
elasticsearch_utils/types.py
elasticsearch_utils/version.py
elasticsearch_utils-0.6.0.dist-info/METADATA
elasticsearch_utils-0.6.0.dist-info/WHEEL
elasticsearch_utils-0.6.0.dist-info/RECORD
